ffxivweather/__init__.py
ffxivweather/forecaster.py
ffxivweather/lang_kind.py
ffxivweather/store/terriTypes.json
ffxivweather/store/weatherKinds.json
ffxivweather/store/weatherRateIndices.json
ffxivweather-1.0.14.dist-info/LICENSE
ffxivweather-1.0.14.dist-info/METADATA
ffxivweather-1.0.14.dist-info/WHEEL
ffxivweather-1.0.14.dist-info/top_level.txt
ffxivweather-1.0.14.dist-info/RECORD
