Metadata-Version: 2.1
Name: ffxivweather
Version: 1.0.14
Summary: FFXIV weather forecast library for Python applications.
Home-page: https://github.com/karashiiro/ffxivweather-py
Author: karashiiro
License: MIT
Classifier: License :: OSI Approved :: MIT License
Classifier: Programming Language :: Python :: 3
Classifier: Programming Language :: Python :: 3.8
License-File: LICENSE
Requires-Dist: jsonpickle
